CLI.cfg
function_map.py
ldapAuth.py
ldapVerify.py
nagios.cmd
nagios_cli.log
nagios_cli.py
printf
setup.cfg
setup.py
template.txt
/usr/local/nagios/var/rw/nagios.cmd
NagiosCli.egg-info/PKG-INFO
NagiosCli.egg-info/SOURCES.txt
NagiosCli.egg-info/dependency_links.txt
NagiosCli.egg-info/requires.txt
NagiosCli.egg-info/top_level.txt