Metadata-Version: 1.0
Name: NagiosCli
Version: 0.9
Summary: CLI for bulk alert management
Home-page: https://opsgerrit.vpn.insnw.net/#/admin/projects/ops/scripts2
Author: instart/ops
Author-email: sanusha@instartlogic.com
License: UNKNOWN
Platform: UNKNOWN
